setup.cfg
setup.py
nsl.stac.experimental.egg-info/PKG-INFO
nsl.stac.experimental.egg-info/SOURCES.txt
nsl.stac.experimental.egg-info/dependency_links.txt
nsl.stac.experimental.egg-info/not-zip-safe
nsl.stac.experimental.egg-info/requires.txt
nsl.stac.experimental.egg-info/top_level.txt
nsl/stac/__init__.py
nsl/stac/client.py
nsl/stac/enum.py
nsl/stac/experimental.py
nsl/stac/utils.py
test/test_client.py