Metadata-Version: 1.2
Name: nsl.stac.experimental
Version: 1.0.1
Summary: gRPC Spatio Temporal Asset Catalog library
Home-page: https://github.com/nearspacelabs/stac-client-python
Author: David Raleigh
Author-email: david@nearspacelabs.com
License: Apache 2.0
Platform: UNKNOWN
Classifier: Programming Language :: Python
Classifier: Programming Language :: Python :: 3
Classifier: Programming Language :: Python :: 3.6
Classifier: Programming Language :: Python :: 3.7
Requires-Python: >3.6.0
